pylsp_jsonrpc/__init__.py
pylsp_jsonrpc/_version.py
pylsp_jsonrpc/dispatchers.py
pylsp_jsonrpc/endpoint.py
pylsp_jsonrpc/exceptions.py
pylsp_jsonrpc/streams.py
python_lsp_jsonrpc-1.1.1.dist-info/LICENSE
python_lsp_jsonrpc-1.1.1.dist-info/METADATA
python_lsp_jsonrpc-1.1.1.dist-info/WHEEL
python_lsp_jsonrpc-1.1.1.dist-info/top_level.txt
python_lsp_jsonrpc-1.1.1.dist-info/RECORD
