Metadata-Version: 2.1
Name: python-lsp-jsonrpc
Version: 1.1.1
Summary: JSON RPC 2.0 server library
Author: Python Language Server Contributors
License: MIT
Project-URL: Homepage, https://github.com/python-lsp/python-lsp-jsonrpc
Classifier: License :: OSI Approved :: MIT License
Requires-Python: >=3.8
License-File: LICENSE
Requires-Dist: ujson>=3.0.0
Provides-Extra: test
Requires-Dist: pylint; extra == "test"
Requires-Dist: pycodestyle; extra == "test"
Requires-Dist: pyflakes; extra == "test"
Requires-Dist: pytest; extra == "test"
Requires-Dist: pytest-cov; extra == "test"
Requires-Dist: coverage; extra == "test"
